pancloud/__init__.py
pancloud/credentials.py
pancloud/directorysync.py
pancloud/event.py
pancloud/exceptions.py
pancloud/httpclient.py
pancloud/logging.py
pancloud-1.0.0.dist-info/DESCRIPTION.rst
pancloud-1.0.0.dist-info/METADATA
pancloud-1.0.0.dist-info/RECORD
pancloud-1.0.0.dist-info/WHEEL
pancloud-1.0.0.dist-info/metadata.json
pancloud-1.0.0.dist-info/top_level.txt
