Metadata-Version: 2.0
Name: pancloud
Version: 1.0.0
Summary: Python idiomatic SDK for the Palo Alto Networks Application Framework.
Home-page: https://github.com/PaloAltoNetworks/pancloud
Author: Steven Serrata
Author-email: sserrata@paloaltonetworks.com
License: ISC license
Keywords: pancloud
Platform: UNKNOWN
Classifier: Development Status :: 4 - Beta
Classifier: Intended Audience :: Developers
Classifier: License :: OSI Approved :: ISC License (ISCL)
Classifier: Natural Language :: English
Classifier: Programming Language :: Python :: 2
Classifier: Programming Language :: Python :: 2.7
Classifier: Programming Language :: Python :: 3
Classifier: Programming Language :: Python :: 3.5
Classifier: Programming Language :: Python :: 3.6
Requires-Dist: cffi
Requires-Dist: cryptography
Requires-Dist: requests
Requires-Dist: requests-oauthlib
